README.md
datek_app_utils/__init__.py
datek_app_utils/async_utils.py
datek_app_utils/env_config/__init__.py
datek_app_utils/env_config/base.py
datek_app_utils/env_config/bool_type.py
datek_app_utils/env_config/errors.py
datek_app_utils/env_config/utils.py
datek_app_utils/log.py
datek_app_utils/py.typed
datek_app_utils-0.4.0.dist-info/LICENSE
datek_app_utils-0.4.0.dist-info/METADATA
datek_app_utils-0.4.0.dist-info/WHEEL
datek_app_utils-0.4.0.dist-info/RECORD
