Metadata-Version: 2.1
Name: datek_app_utils
Version: 0.4.0
Summary: Utilities for building applications
Home-page: https://github.com/DAtek/datek-app-utils/
License: MIT
Author: Attila Dudas
Author-email: dudasa7@gmail.com
Requires-Python: >=3.8,<4.0
Classifier: License :: OSI Approved :: MIT License
Classifier: Programming Language :: Python :: 3
Classifier: Programming Language :: Python :: 3.8
Classifier: Programming Language :: Python :: 3.9
Classifier: Programming Language :: Python :: 3.10
Classifier: Programming Language :: Python :: 3.11
Classifier: Programming Language :: Python :: 3.12
Project-URL: Repository, https://github.com/DAtek/datek-app-utils/
